{
  "currency": "USD",
  "points": [
    { "date": "2026-06-10", "cost": 2.04, "cpa": 0.68, "roi": 605.0, "conversions": 3 },
    { "date": "2026-06-11", "cost": 21.0, "cpa": 0.92, "roi": 320.0, "conversions": 14 },
    { "date": "2026-06-12", "cost": 44.36, "cpa": 1.23, "roi": 161.47, "conversions": 36 },
    { "date": "2026-06-13", "cost": 52.0, "cpa": 0.8, "roi": 92.0, "conversions": 45 },
    { "date": "2026-06-14", "cost": 49.0, "cpa": 1.12, "roi": 64.0, "conversions": 50 },
    { "date": "2026-06-15", "cost": 53.0, "cpa": 0.88, "roi": 57.0, "conversions": 57 },
    { "date": "2026-06-16", "cost": 55.65, "cpa": 0.99, "roi": 60.0, "conversions": 63 },
    { "date": "2026-06-17", "cost": 58.0, "cpa": 1.28, "roi": 78.0, "conversions": 70 },
    { "date": "2026-06-18", "cost": 61.0, "cpa": 0.95, "roi": 105.0, "conversions": 76 },
    { "date": "2026-06-19", "cost": 63.5, "cpa": 1.05, "roi": 140.0, "conversions": 82 }
  ]
}
